{
  "cli": {
    "version": ">= 5.2.0"
  },
  "build": {
    "development": {
      "developmentClient": true,
      "distribution": "internal",
      "ios": {
        "simulator": true
      }
    },
    "preview": {
      "distribution": "internal",
      "ios": {
        "simulator": false,
        "bundleIdentifier": "com.warenbuchung.app"
      }
    },
    "production": {
      "distribution": "store",
      "ios": {
        "bundleIdentifier": "com.warenbuchung.app"
      }
    }
  },
  "submit": {
    "production": {
      "ios": {
        "appleId": "deine-apple-id@email.com",
        "ascAppId": "1234567890",
        "appleTeamId": "DEIN_TEAM_ID"
      }
    }
  }
}







































